COPYING
MANIFEST.in
README.md
setup.py
mempulse/__init__.py
mempulse/ctracer.py
mempulse/pytracer.py
mempulse.egg-info/PKG-INFO
mempulse.egg-info/SOURCES.txt
mempulse.egg-info/dependency_links.txt
mempulse.egg-info/requires.txt
mempulse.egg-info/top_level.txt
mempulse/ext/__init__.py
mempulse/ext/tracer.c
mempulse/ext/uthash.h